recipe_scrapers/__init__.py
recipe_scrapers/__version__.py
recipe_scrapers/_abstract.py
recipe_scrapers/_exceptions.py
recipe_scrapers/_factory.py
recipe_scrapers/_grouping_utils.py
recipe_scrapers/_opengraph.py
recipe_scrapers/_schemaorg.py
recipe_scrapers/_utils.py
recipe_scrapers/_warnings.py
recipe_scrapers/abeautifulmess.py
recipe_scrapers/aberlehome.py
recipe_scrapers/abril.py
recipe_scrapers/abuelascounter.py
recipe_scrapers/acouplecooks.py
recipe_scrapers/acozykitchen.py
recipe_scrapers/addapinch.py
recipe_scrapers/adozensundays.py
recipe_scrapers/afarmgirlsdabbles.py
recipe_scrapers/afghankitchenrecipes.py
recipe_scrapers/aflavorjournal.py
recipe_scrapers/ahealthysliceoflife.py
recipe_scrapers/akispetretzikis.py
recipe_scrapers/albertheijn.py
recipe_scrapers/aldi.py
recipe_scrapers/aldinord.py
recipe_scrapers/aldisued.py
recipe_scrapers/aldisuisse.py
recipe_scrapers/alexandracooks.py
recipe_scrapers/alittlebityummy.py
recipe_scrapers/allrecipes.py
recipe_scrapers/allthehealthythings.py
recipe_scrapers/alltommat.py
recipe_scrapers/altonbrown.py
recipe_scrapers/amazingoriental.py
recipe_scrapers/amazingribs.py
recipe_scrapers/ambitiouskitchen.py
recipe_scrapers/ameessavorydish.py
recipe_scrapers/americastestkitchen.py
recipe_scrapers/archanaskitchen.py
recipe_scrapers/argiro.py
recipe_scrapers/arla.py
recipe_scrapers/atelierdeschefs.py
recipe_scrapers/averiecooks.py
recipe_scrapers/bakels.py
recipe_scrapers/bakerbynature.py
recipe_scrapers/bakewithzoha.py
recipe_scrapers/bakingmischief.py
recipe_scrapers/bakingsense.py
recipe_scrapers/barefeetinthekitchen.py
recipe_scrapers/barefootcontessa.py
recipe_scrapers/barefootinthepines.py
recipe_scrapers/bbcfood.py
recipe_scrapers/bbcgoodfood.py
recipe_scrapers/bestrecipes.py
recipe_scrapers/betterfoodguru.py
recipe_scrapers/bettybossi.py
recipe_scrapers/bettycrocker.py
recipe_scrapers/beyondfrosting.py
recipe_scrapers/biancazapatka.py
recipe_scrapers/bigoven.py
recipe_scrapers/bitsofcarey.py
recipe_scrapers-15.9.0.dist-info/licenses/LICENSE
recipe_scrapers-15.9.0.dist-info/METADATA
recipe_scrapers-15.9.0.dist-info/WHEEL
recipe_scrapers-15.9.0.dist-info/top_level.txt
recipe_scrapers-15.9.0.dist-info/RECORD
