Metadata-Version: 2.4
Name: recipe_scrapers
Version: 15.9.0
Summary: Python package, scraping recipes from all over the internet
Author-email: Hristo Harsev <r+pypi@hharsev.com>, James Addison <james@reciperadar.com>
Maintainer-email: Hristo Harsev <r+pypi@hharsev.com>, James Addison <james@reciperadar.com>
License: MIT License
Project-URL: Homepage, https://github.com/hhursev/recipe-scrapers/
Keywords: python,recipes,scraper,harvest,recipe-scraper,recipe-scrapers
Classifier: Programming Language :: Python :: 3
Classifier: Programming Language :: Python :: 3 :: Only
Classifier: Programming Language :: Python :: 3.9
Classifier: Programming Language :: Python :: 3.10
Classifier: Programming Language :: Python :: 3.11
Classifier: Programming Language :: Python :: 3.12
Classifier: Programming Language :: Python :: 3.13
Classifier: License :: OSI Approved :: MIT License
Classifier: Intended Audience :: Developers
Classifier: Operating System :: OS Independent
Classifier: Topic :: Internet :: WWW/HTTP
Classifier: Topic :: Software Development :: Libraries
Requires-Python: >=3.9
License-File: LICENSE
Requires-Dist: beautifulsoup4>=4.12.3
Requires-Dist: extruct>=0.17.0
Requires-Dist: isodate>=0.6.1
Provides-Extra: online
Requires-Dist: requests>=2.31.0; extra == "online"
Provides-Extra: docs
Requires-Dist: mkdocs>=1.6.1; extra == "docs"
Requires-Dist: mkdocs-material>=9.5.48; extra == "docs"
Requires-Dist: mkdocstrings>=0.27.0; extra == "docs"
Requires-Dist: mkdocstrings-python>=1.12.2; extra == "docs"
Requires-Dist: markdown-exec>=1.10.0; extra == "docs"
Provides-Extra: tests
Requires-Dist: coverage>=7.6.9; extra == "tests"
Requires-Dist: unittest-parallel>=1.7.0; extra == "tests"
Provides-Extra: linters
Requires-Dist: pre-commit==4.0.1; extra == "linters"
Requires-Dist: black==24.10.0; extra == "linters"
Requires-Dist: flake8==7.1.1; extra == "linters"
Requires-Dist: pep8-naming==0.14.1; extra == "linters"
Requires-Dist: mypy==1.14.0; extra == "linters"
Requires-Dist: types-beautifulsoup4; extra == "linters"
Requires-Dist: types-requests; extra == "linters"
Provides-Extra: dev
Requires-Dist: recipe-scrapers[docs,linters,tests]; extra == "dev"
Provides-Extra: all
Requires-Dist: recipe_scrapers[dev,docs,linters,online,tests]; extra == "all"
Dynamic: license-file
